allure3_server/__init__.py
allure3_server/__version__.py
allure3_server/allurerc.json
allure3_server/check_env.py
allure3_server/cli.py
allure3_server/config.py
allure3_server/main.py
allure3_server/static/favicon.png
allure3_server/static/swagger-ui-bundle.js
allure3_server/static/swagger-ui.css
allure3_server-1.5.0.dist-info/METADATA
allure3_server-1.5.0.dist-info/WHEEL
allure3_server-1.5.0.dist-info/entry_points.txt
allure3_server-1.5.0.dist-info/licenses/LICENSE
allure3_server-1.5.0.dist-info/RECORD
