Metadata-Version: 2.4
Name: allure3-server
Version: 1.5.0
Author-email: mikigo <mikigo@foxmail.com>
License: Apache2.0
License-File: LICENSE
Requires-Python: >=3.6
Requires-Dist: click
Requires-Dist: fastapi
Requires-Dist: python-multipart
Requires-Dist: uvicorn
